genomvar/__init__.py
genomvar/__main__.py
genomvar/cmdutils.py
genomvar/utils.py
genomvar/variant.py
genomvar/variantops.py
genomvar/varset.py
genomvar/vcf.py
genomvar/tmpl/vcf_head_base.tmpl
genomvar/tmpl/vcf_head_info.tmpl
genomvar/tmpl/vcf_head_simple.tmpl
genomvar/tmpl/vcf_row.tmpl
genomvar-0.1.13.dist-info/LICENSE
genomvar-0.1.13.dist-info/METADATA
genomvar-0.1.13.dist-info/WHEEL
genomvar-0.1.13.dist-info/top_level.txt
genomvar-0.1.13.dist-info/RECORD
