Metadata-Version: 2.1
Name: genomvar
Version: 0.1.13
Summary: Sequence variant analysis in Python
Home-page: http://relativity.nprog.local/mikpom/genomvar
Author: Mikhail Pomaznoy
Author-email: mikpom@mailbox.org
License: BSD
Keywords: Bioinformatics,Computational Biology
Platform: UNKNOWN
Classifier: Intended Audience :: Science/Research
Classifier: Programming Language :: Python :: 3
Classifier: Topic :: Scientific/Engineering :: Bio-Informatics
Classifier: Topic :: Software Development :: Libraries
Requires-Dist: bx-python
Requires-Dist: jinja2
Requires-Dist: pysam
